[{"seq":0.0,"peak":520.2,"peakTime":9.0,"sumAfter16":1536.5},{"seq":1.0,"peak":504.3,"peakTime":9.0,"sumAfter16":1569.5},{"seq":2.0,"peak":471.7,"peakTime":10.0,"sumAfter16":1602.6},{"seq":3.0,"peak":503.0,"peakTime":10.0,"sumAfter16":1603.1},{"seq":4.0,"peak":497.2,"peakTime":10.0,"sumAfter16":1636.1},{"seq":5.0,"peak":481.3,"peakTime":10.0,"sumAfter16":1669.2},{"seq":6.0,"peak":471.4,"peakTime":10.0,"sumAfter16":1669.7},{"seq":7.0,"peak":465.5,"peakTime":10.0,"sumAfter16":1702.8},{"seq":8.0,"peak":449.6,"peakTime":10.0,"sumAfter16":1735.8},{"seq":9.0,"peak":506.9,"peakTime":9.0,"sumAfter16":1564.4},{"seq":10.0,"peak":491.0,"peakTime":9.0,"sumAfter16":1597.4},{"seq":11.0,"peak":474.7,"peakTime":10.0,"sumAfter16":1630.5},{"seq":12.0,"peak":506.1,"peakTime":10.0,"sumAfter16":1631.0},{"seq":13.0,"peak":500.2,"peakTime":10.0,"sumAfter16":1664.0},{"seq":14.0,"peak":484.3,"peakTime":10.0,"sumAfter16":1697.1},{"seq":15.0,"peak":474.4,"peakTime":10.0,"sumAfter16":1697.6},{"seq":16.0,"peak":468.5,"peakTime":10.0,"sumAfter16":1730.7},{"seq":17.0,"peak":452.6,"peakTime":10.0,"sumAfter16":1763.7},{"seq":18.0,"peak":483.2,"peakTime":10.0,"sumAfter16":1592.3},{"seq":19.0,"peak":477.4,"peakTime":10.0,"sumAfter16":1625.3},{"seq":20.0,"peak":461.5,"peakTime":10.0,"sumAfter16":1658.4},{"seq":21.0,"peak":492.8,"peakTime":10.0,"sumAfter16":1658.9},{"seq":22.0,"peak":486.9,"peakTime":10.0,"sumAfter16":1691.9},{"seq":23.0,"peak":471.0,"peakTime":10.0,"sumAfter16":1725.0},{"seq":24.0,"peak":461.1,"peakTime":10.0,"sumAfter16":1725.5},{"seq":25.0,"peak":455.2,"peakTime":10.0,"sumAfter16":1758.5},{"seq":26.0,"peak":439.3,"peakTime":10.0,"sumAfter16":1791.6},{"seq":27.0,"peak":502.6,"peakTime":10.0,"sumAfter16":1643.6},{"seq":28.0,"peak":496.7,"peakTime":10.0,"sumAfter16":1676.6},{"seq":29.0,"peak":480.8,"peakTime":10.0,"sumAfter16":1709.7},{"seq":30.0,"peak":512.1,"peakTime":10.0,"sumAfter16":1710.2},{"seq":31.0,"peak":506.3,"peakTime":10.0,"sumAfter16":1743.2},{"seq":32.0,"peak":490.4,"peakTime":10.0,"sumAfter16":1776.3},{"seq":33.0,"peak":480.5,"peakTime":10.0,"sumAfter16":1776.8},{"seq":34.0,"peak":474.6,"peakTime":10.0,"sumAfter16":1809.9},{"seq":35.0,"peak":458.7,"peakTime":10.0,"sumAfter16":1842.9},{"seq":36.0,"peak":505.6,"peakTime":10.0,"sumAfter16":1671.5},{"seq":37.0,"peak":499.8,"peakTime":10.0,"sumAfter16":1704.5},{"seq":38.0,"peak":483.8,"peakTime":10.0,"sumAfter16":1737.6},{"seq":39.0,"peak":515.2,"peakTime":10.0,"sumAfter16":1738.1},{"seq":40.0,"peak":509.3,"peakTime":10.0,"sumAfter16":1771.1},{"seq":41.0,"peak":493.4,"peakTime":10.0,"sumAfter16":1804.2},{"seq":42.0,"peak":483.5,"peakTime":10.0,"sumAfter16":1804.7},{"seq":43.0,"peak":477.6,"peakTime":10.0,"sumAfter16":1837.7},{"seq":44.0,"peak":470.0,"peakTime":11.0,"sumAfter16":1870.8},{"seq":45.0,"peak":492.3,"peakTime":10.0,"sumAfter16":1699.4},{"seq":46.0,"peak":486.5,"peakTime":10.0,"sumAfter16":1732.4},{"seq":47.0,"peak":470.6,"peakTime":10.0,"sumAfter16":1765.5},{"seq":48.0,"peak":501.9,"peakTime":10.0,"sumAfter16":1766.0},{"seq":49.0,"peak":496.0,"peakTime":10.0,"sumAfter16":1799.0},{"seq":50.0,"peak":480.1,"peakTime":10.0,"sumAfter16":1832.1},{"seq":51.0,"peak":470.2,"peakTime":10.0,"sumAfter16":1832.6},{"seq":52.0,"peak":478.9,"peakTime":11.0,"sumAfter16":1865.6},{"seq":53.0,"peak":473.1,"peakTime":11.0,"sumAfter16":1898.7},{"seq":54.0,"peak":451.5,"peakTime":10.0,"sumAfter16":1750.7},{"seq":55.0,"peak":445.7,"peakTime":10.0,"sumAfter16":1783.7},{"seq":56.0,"peak":429.8,"peakTime":10.0,"sumAfter16":1816.8},{"seq":57.0,"peak":461.1,"peakTime":10.0,"sumAfter16":1817.3},{"seq":58.0,"peak":461.2,"peakTime":11.0,"sumAfter16":1850.3},{"seq":59.0,"peak":455.4,"peakTime":11.0,"sumAfter16":1883.4},{"seq":60.0,"peak":451.7,"peakTime":11.0,"sumAfter16":1883.9},{"seq":61.0,"peak":470.8,"peakTime":11.0,"sumAfter16":1917.0},{"seq":62.0,"peak":465.0,"peakTime":11.0,"sumAfter16":1950.0},{"seq":63.0,"peak":454.5,"peakTime":10.0,"sumAfter16":1778.6},{"seq":64.0,"peak":448.7,"peakTime":10.0,"sumAfter16":1811.6},{"seq":65.0,"peak":436.5,"peakTime":11.0,"sumAfter16":1844.7},{"seq":66.0,"peak":464.1,"peakTime":10.0,"sumAfter16":1845.2},{"seq":67.0,"peak":475.4,"peakTime":11.0,"sumAfter16":1878.2},{"seq":68.0,"peak":469.6,"peakTime":11.0,"sumAfter16":1911.3},{"seq":69.0,"peak":465.9,"peakTime":11.0,"sumAfter16":1911.8},{"seq":70.0,"peak":485.0,"peakTime":11.0,"sumAfter16":1944.8},{"seq":71.0,"peak":479.1,"peakTime":11.0,"sumAfter16":1977.9},{"seq":72.0,"peak":441.2,"peakTime":10.0,"sumAfter16":1806.5},{"seq":73.0,"peak":445.3,"peakTime":11.0,"sumAfter16":1839.5},{"seq":74.0,"peak":439.5,"peakTime":11.0,"sumAfter16":1872.6},{"seq":75.0,"peak":459.3,"peakTime":11.0,"sumAfter16":1873.1},{"seq":76.0,"peak":478.4,"peakTime":11.0,"sumAfter16":1906.1},{"seq":77.0,"peak":472.6,"peakTime":11.0,"sumAfter16":1939.2},{"seq":78.0,"peak":468.9,"peakTime":11.0,"sumAfter16":1939.7},{"seq":79.0,"peak":488.0,"peakTime":11.0,"sumAfter16":1972.7},{"seq":80.0,"peak":482.2,"peakTime":11.0,"sumAfter16":2005.8},{"seq":108.0,"peak":509.3,"peakTime":10.0,"sumAfter16":1676.1},{"seq":109.0,"peak":503.4,"peakTime":10.0,"sumAfter16":1709.2},{"seq":110.0,"peak":487.5,"peakTime":10.0,"sumAfter16":1742.2},{"seq":111.0,"peak":518.8,"peakTime":10.0,"sumAfter16":1742.7},{"seq":112.0,"peak":513.0,"peakTime":10.0,"sumAfter16":1775.8},{"seq":113.0,"peak":497.1,"peakTime":10.0,"sumAfter16":1808.9},{"seq":114.0,"peak":487.2,"peakTime":10.0,"sumAfter16":1809.3},{"seq":115.0,"peak":481.3,"peakTime":10.0,"sumAfter16":1842.4},{"seq":116.0,"peak":472.1,"peakTime":11.0,"sumAfter16":1875.5},{"seq":117.0,"peak":512.3,"peakTime":10.0,"sumAfter16":1704.0},{"seq":118.0,"peak":506.4,"peakTime":10.0,"sumAfter16":1737.1},{"seq":119.0,"peak":490.5,"peakTime":10.0,"sumAfter16":1770.1},{"seq":120.0,"peak":521.9,"peakTime":10.0,"sumAfter16":1770.6},{"seq":121.0,"peak":516.0,"peakTime":10.0,"sumAfter16":1803.7},{"seq":122.0,"peak":500.1,"peakTime":10.0,"sumAfter16":1836.8},{"seq":123.0,"peak":490.2,"peakTime":10.0,"sumAfter16":1837.2},{"seq":124.0,"peak":492.1,"peakTime":11.0,"sumAfter16":1870.3},{"seq":125.0,"peak":486.3,"peakTime":11.0,"sumAfter16":1903.4},{"seq":126.0,"peak":499.0,"peakTime":10.0,"sumAfter16":1731.9},{"seq":127.0,"peak":493.2,"peakTime":10.0,"sumAfter16":1765.0},{"seq":128.0,"peak":477.2,"peakTime":10.0,"sumAfter16":1798.0},{"seq":129.0,"peak":508.6,"peakTime":10.0,"sumAfter16":1798.5},{"seq":130.0,"peak":502.7,"peakTime":10.0,"sumAfter16":1831.6},{"seq":131.0,"peak":486.8,"peakTime":10.0,"sumAfter16":1864.6},{"seq":132.0,"peak":476.9,"peakTime":10.0,"sumAfter16":1865.1},{"seq":133.0,"peak":495.1,"peakTime":11.0,"sumAfter16":1898.2},{"seq":134.0,"peak":489.3,"peakTime":11.0,"sumAfter16":1931.3},{"seq":135.0,"peak":458.2,"peakTime":10.0,"sumAfter16":1783.2},{"seq":136.0,"peak":452.4,"peakTime":10.0,"sumAfter16":1816.3},{"seq":137.0,"peak":438.5,"peakTime":11.0,"sumAfter16":1849.3},{"seq":138.0,"peak":467.8,"peakTime":10.0,"sumAfter16":1849.8},{"seq":139.0,"peak":477.5,"peakTime":11.0,"sumAfter16":1882.9},{"seq":140.0,"peak":471.6,"peakTime":11.0,"sumAfter16":1916.0},{"seq":141.0,"peak":468.0,"peakTime":11.0,"sumAfter16":1916.4},{"seq":142.0,"peak":487.1,"peakTime":11.0,"sumAfter16":1949.5},{"seq":143.0,"peak":481.2,"peakTime":11.0,"sumAfter16":1982.6},{"seq":144.0,"peak":461.2,"peakTime":10.0,"sumAfter16":1811.1},{"seq":145.0,"peak":458.5,"peakTime":11.0,"sumAfter16":1844.2},{"seq":146.0,"peak":452.7,"peakTime":11.0,"sumAfter16":1877.2},{"seq":147.0,"peak":472.6,"peakTime":11.0,"sumAfter16":1877.7},{"seq":148.0,"peak":491.6,"peakTime":11.0,"sumAfter16":1910.8},{"seq":149.0,"peak":485.8,"peakTime":11.0,"sumAfter16":1943.8},{"seq":150.0,"peak":482.1,"peakTime":11.0,"sumAfter16":1944.3},{"seq":151.0,"peak":501.2,"peakTime":11.0,"sumAfter16":1977.4},{"seq":152.0,"peak":495.4,"peakTime":11.0,"sumAfter16":2010.5},{"seq":153.0,"peak":447.9,"peakTime":10.0,"sumAfter16":1839.0},{"seq":154.0,"peak":461.6,"peakTime":11.0,"sumAfter16":1872.1},{"seq":155.0,"peak":455.7,"peakTime":11.0,"sumAfter16":1905.1},{"seq":156.0,"peak":475.6,"peakTime":11.0,"sumAfter16":1905.6},{"seq":157.0,"peak":494.7,"peakTime":11.0,"sumAfter16":1938.7},{"seq":158.0,"peak":488.8,"peakTime":11.0,"sumAfter16":1971.7},{"seq":159.0,"peak":485.2,"peakTime":11.0,"sumAfter16":1972.2},{"seq":160.0,"peak":504.2,"peakTime":11.0,"sumAfter16":2005.3},{"seq":161.0,"peak":498.4,"peakTime":11.0,"sumAfter16":2038.4},{"seq":216.0,"peak":442.6,"peakTime":10.0,"sumAfter16":1815.7},{"seq":217.0,"peak":451.1,"peakTime":11.0,"sumAfter16":1848.8},{"seq":218.0,"peak":445.2,"peakTime":11.0,"sumAfter16":1881.9},{"seq":219.0,"peak":465.1,"peakTime":11.0,"sumAfter16":1882.3},{"seq":220.0,"peak":484.2,"peakTime":11.0,"sumAfter16":1915.4},{"seq":221.0,"peak":478.3,"peakTime":11.0,"sumAfter16":1948.5},{"seq":222.0,"peak":474.7,"peakTime":11.0,"sumAfter16":1949.0},{"seq":223.0,"peak":493.7,"peakTime":11.0,"sumAfter16":1982.0},{"seq":224.0,"peak":487.9,"peakTime":11.0,"sumAfter16":2015.1},{"seq":225.0,"peak":446.2,"peakTime":11.0,"sumAfter16":1843.6},{"seq":226.0,"peak":465.2,"peakTime":11.0,"sumAfter16":1876.7},{"seq":227.0,"peak":459.4,"peakTime":11.0,"sumAfter16":1909.8},{"seq":228.0,"peak":479.3,"peakTime":11.0,"sumAfter16":1910.2},{"seq":229.0,"peak":498.3,"peakTime":11.0,"sumAfter16":1943.3},{"seq":230.0,"peak":492.5,"peakTime":11.0,"sumAfter16":1976.4},{"seq":231.0,"peak":488.8,"peakTime":11.0,"sumAfter16":1976.8},{"seq":232.0,"peak":507.9,"peakTime":11.0,"sumAfter16":2009.9},{"seq":233.0,"peak":502.1,"peakTime":11.0,"sumAfter16":2043.0},{"seq":234.0,"peak":449.2,"peakTime":11.0,"sumAfter16":1871.5},{"seq":235.0,"peak":468.3,"peakTime":11.0,"sumAfter16":1904.6},{"seq":236.0,"peak":462.4,"peakTime":11.0,"sumAfter16":1937.7},{"seq":237.0,"peak":482.3,"peakTime":11.0,"sumAfter16":1938.1},{"seq":238.0,"peak":501.4,"peakTime":11.0,"sumAfter16":1971.2},{"seq":239.0,"peak":495.5,"peakTime":11.0,"sumAfter16":2004.3},{"seq":240.0,"peak":491.9,"peakTime":11.0,"sumAfter16":2004.7},{"seq":241.0,"peak":510.9,"peakTime":11.0,"sumAfter16":2037.8},{"seq":242.0,"peak":505.1,"peakTime":11.0,"sumAfter16":2070.9},{"seq":351.0,"peak":513.5,"peakTime":10.0,"sumAfter16":1698.1},{"seq":352.0,"peak":507.6,"peakTime":10.0,"sumAfter16":1731.2},{"seq":353.0,"peak":491.7,"peakTime":10.0,"sumAfter16":1764.3},{"seq":354.0,"peak":523.0,"peakTime":10.0,"sumAfter16":1764.7},{"seq":355.0,"peak":517.2,"peakTime":10.0,"sumAfter16":1797.8},{"seq":356.0,"peak":501.3,"peakTime":10.0,"sumAfter16":1830.9},{"seq":357.0,"peak":491.4,"peakTime":10.0,"sumAfter16":1831.3},{"seq":358.0,"peak":488.9,"peakTime":11.0,"sumAfter16":1864.4},{"seq":359.0,"peak":483.0,"peakTime":11.0,"sumAfter16":1897.5},{"seq":360.0,"peak":516.5,"peakTime":10.0,"sumAfter16":1726.0},{"seq":361.0,"peak":510.7,"peakTime":10.0,"sumAfter16":1759.1},{"seq":362.0,"peak":494.7,"peakTime":10.0,"sumAfter16":1792.2},{"seq":363.0,"peak":526.1,"peakTime":10.0,"sumAfter16":1792.6},{"seq":364.0,"peak":520.2,"peakTime":10.0,"sumAfter16":1825.7},{"seq":365.0,"peak":504.3,"peakTime":10.0,"sumAfter16":1858.8},{"seq":366.0,"peak":494.4,"peakTime":10.0,"sumAfter16":1859.2},{"seq":367.0,"peak":503.0,"peakTime":11.0,"sumAfter16":1892.3},{"seq":368.0,"peak":497.2,"peakTime":11.0,"sumAfter16":1925.4},{"seq":369.0,"peak":503.2,"peakTime":10.0,"sumAfter16":1753.9},{"seq":370.0,"peak":497.4,"peakTime":10.0,"sumAfter16":1787.0},{"seq":371.0,"peak":481.5,"peakTime":10.0,"sumAfter16":1820.1},{"seq":372.0,"peak":512.8,"peakTime":10.0,"sumAfter16":1820.5},{"seq":373.0,"peak":506.9,"peakTime":10.0,"sumAfter16":1853.6},{"seq":374.0,"peak":491.0,"peakTime":10.0,"sumAfter16":1886.7},{"seq":375.0,"peak":487.0,"peakTime":11.0,"sumAfter16":1887.1},{"seq":376.0,"peak":506.1,"peakTime":11.0,"sumAfter16":1920.2},{"seq":377.0,"peak":500.2,"peakTime":11.0,"sumAfter16":1953.3},{"seq":378.0,"peak":462.4,"peakTime":10.0,"sumAfter16":1805.2},{"seq":379.0,"peak":456.6,"peakTime":10.0,"sumAfter16":1838.3},{"seq":380.0,"peak":449.5,"peakTime":11.0,"sumAfter16":1871.4},{"seq":381.0,"peak":472.0,"peakTime":10.0,"sumAfter16":1871.8},{"seq":382.0,"peak":488.4,"peakTime":11.0,"sumAfter16":1904.9},{"seq":383.0,"peak":482.6,"peakTime":11.0,"sumAfter16":1938.0},{"seq":384.0,"peak":478.9,"peakTime":11.0,"sumAfter16":1938.4},{"seq":385.0,"peak":498.0,"peakTime":11.0,"sumAfter16":1971.5},{"seq":386.0,"peak":492.1,"peakTime":11.0,"sumAfter16":2004.6},{"seq":387.0,"peak":465.4,"peakTime":10.0,"sumAfter16":1833.1},{"seq":388.0,"peak":469.5,"peakTime":11.0,"sumAfter16":1866.2},{"seq":389.0,"peak":463.6,"peakTime":11.0,"sumAfter16":1899.3},{"seq":390.0,"peak":483.5,"peakTime":11.0,"sumAfter16":1899.7},{"seq":391.0,"peak":502.6,"peakTime":11.0,"sumAfter16":1932.8},{"seq":392.0,"peak":496.7,"peakTime":11.0,"sumAfter16":1965.9},{"seq":393.0,"peak":493.1,"peakTime":11.0,"sumAfter16":1966.3},{"seq":394.0,"peak":512.1,"peakTime":11.0,"sumAfter16":1999.4},{"seq":395.0,"peak":506.3,"peakTime":11.0,"sumAfter16":2032.5},{"seq":396.0,"peak":453.4,"peakTime":11.0,"sumAfter16":1861.0},{"seq":397.0,"peak":472.5,"peakTime":11.0,"sumAfter16":1894.1},{"seq":398.0,"peak":466.7,"peakTime":11.0,"sumAfter16":1927.1},{"seq":399.0,"peak":486.5,"peakTime":11.0,"sumAfter16":1927.6},{"seq":400.0,"peak":505.6,"peakTime":11.0,"sumAfter16":1960.7},{"seq":401.0,"peak":499.8,"peakTime":11.0,"sumAfter16":1993.8},{"seq":402.0,"peak":496.1,"peakTime":11.0,"sumAfter16":1994.2},{"seq":403.0,"peak":515.2,"peakTime":11.0,"sumAfter16":2027.3},{"seq":404.0,"peak":509.3,"peakTime":11.0,"sumAfter16":2060.4},{"seq":459.0,"peak":446.8,"peakTime":10.0,"sumAfter16":1837.7},{"seq":460.0,"peak":462.0,"peakTime":11.0,"sumAfter16":1870.8},{"seq":461.0,"peak":456.2,"peakTime":11.0,"sumAfter16":1903.9},{"seq":462.0,"peak":476.0,"peakTime":11.0,"sumAfter16":1904.4},{"seq":463.0,"peak":495.1,"peakTime":11.0,"sumAfter16":1937.4},{"seq":464.0,"peak":489.3,"peakTime":11.0,"sumAfter16":1970.5},{"seq":465.0,"peak":485.6,"peakTime":11.0,"sumAfter16":1971.0},{"seq":466.0,"peak":504.7,"peakTime":11.0,"sumAfter16":2004.0},{"seq":467.0,"peak":498.8,"peakTime":11.0,"sumAfter16":2037.1},{"seq":468.0,"peak":457.1,"peakTime":11.0,"sumAfter16":1865.6},{"seq":469.0,"peak":476.2,"peakTime":11.0,"sumAfter16":1898.7},{"seq":470.0,"peak":470.3,"peakTime":11.0,"sumAfter16":1931.8},{"seq":471.0,"peak":490.2,"peakTime":11.0,"sumAfter16":1932.3},{"seq":472.0,"peak":509.3,"peakTime":11.0,"sumAfter16":1965.3},{"seq":473.0,"peak":503.4,"peakTime":11.0,"sumAfter16":1998.4},{"seq":474.0,"peak":499.8,"peakTime":11.0,"sumAfter16":1998.9},{"seq":475.0,"peak":518.8,"peakTime":11.0,"sumAfter16":2031.9},{"seq":476.0,"peak":513.0,"peakTime":11.0,"sumAfter16":2065.0},{"seq":477.0,"peak":460.1,"peakTime":11.0,"sumAfter16":1893.5},{"seq":478.0,"peak":479.2,"peakTime":11.0,"sumAfter16":1926.6},{"seq":479.0,"peak":473.4,"peakTime":11.0,"sumAfter16":1959.7},{"seq":480.0,"peak":493.2,"peakTime":11.0,"sumAfter16":1960.1},{"seq":481.0,"peak":512.3,"peakTime":11.0,"sumAfter16":1993.2},{"seq":482.0,"peak":506.4,"peakTime":11.0,"sumAfter16":2026.3},{"seq":483.0,"peak":502.8,"peakTime":11.0,"sumAfter16":2026.8},{"seq":484.0,"peak":521.9,"peakTime":11.0,"sumAfter16":2059.8},{"seq":485.0,"peak":516.0,"peakTime":11.0,"sumAfter16":2092.9},{"seq":702.0,"peak":447.1,"peakTime":11.0,"sumAfter16":1859.8},{"seq":703.0,"peak":466.2,"peakTime":11.0,"sumAfter16":1892.8},{"seq":704.0,"peak":460.4,"peakTime":11.0,"sumAfter16":1925.9},{"seq":705.0,"peak":480.2,"peakTime":11.0,"sumAfter16":1926.4},{"seq":706.0,"peak":499.3,"peakTime":11.0,"sumAfter16":1959.4},{"seq":707.0,"peak":493.5,"peakTime":11.0,"sumAfter16":1992.5},{"seq":708.0,"peak":489.8,"peakTime":11.0,"sumAfter16":1993.0},{"seq":709.0,"peak":508.9,"peakTime":11.0,"sumAfter16":2026.0},{"seq":710.0,"peak":503.0,"peakTime":11.0,"sumAfter16":2059.1},{"seq":711.0,"peak":461.3,"peakTime":11.0,"sumAfter16":1887.7},{"seq":712.0,"peak":480.4,"peakTime":11.0,"sumAfter16":1920.7},{"seq":713.0,"peak":474.5,"peakTime":11.0,"sumAfter16":1953.8},{"seq":714.0,"peak":494.4,"peakTime":11.0,"sumAfter16":1954.3},{"seq":715.0,"peak":513.5,"peakTime":11.0,"sumAfter16":1987.3},{"seq":716.0,"peak":507.6,"peakTime":11.0,"sumAfter16":2020.4},{"seq":717.0,"peak":504.0,"peakTime":11.0,"sumAfter16":2020.9},{"seq":718.0,"peak":523.0,"peakTime":11.0,"sumAfter16":2053.9},{"seq":719.0,"peak":517.2,"peakTime":11.0,"sumAfter16":2087.0},{"seq":720.0,"peak":464.3,"peakTime":11.0,"sumAfter16":1915.6},{"seq":721.0,"peak":483.4,"peakTime":11.0,"sumAfter16":1948.6},{"seq":722.0,"peak":477.6,"peakTime":11.0,"sumAfter16":1981.7},{"seq":723.0,"peak":497.4,"peakTime":11.0,"sumAfter16":1982.2},{"seq":724.0,"peak":516.5,"peakTime":11.0,"sumAfter16":2015.2},{"seq":725.0,"peak":510.7,"peakTime":11.0,"sumAfter16":2048.3},{"seq":726.0,"peak":507.0,"peakTime":11.0,"sumAfter16":2048.8},{"seq":727.0,"peak":526.1,"peakTime":11.0,"sumAfter16":2081.8},{"seq":728.0,"peak":520.2,"peakTime":11.0,"sumAfter16":2114.9}]